{
    "header": {
        "title": "Loftie Ellis",
        "tagline": "Trying to center a div in a div. And one day climb 8a.",
        "bg_img": "images/header-bg.jpg",
        "has_nav": true,
        "has_social": true
    },
    "footer": {
        "content": "&copy; All rights reserved.",
        "links": [
            {
                "text": "Made with Stackbit",
                "url": "https://www.stackbit.com",
                "new_window": true
            }
        ]
    },
    "palette": "yellow",
    "title": "Stackbit Fjord Theme"
}